minder/__init__.py
minder/__main__.py
minder/api/__init__.py
minder/api/main.py
minder/api/models.py
minder/api/middleware/__init__.py
minder/api/middleware/cors.py
minder/api/routers/__init__.py
minder/api/routers/generator_router.py
minder/api/routers/proxy_router.py
minder/api/routers/service_router.py
minder/cli/__init__.py
minder/cli/api_cli.py
minder/cli/launcher_cli.py
minder/cli/main.py
minder/cli/web_cli.py
minder/client/__init__.py
minder/client/api_client.py
minder/client/exceptions.py
minder/client/mcp_minder.py
minder/core/__init__.py
minder/core/generator.py
minder/core/launcher.py
minder/core/mcp_builder.py
minder/core/mcp_proxy.py
minder/core/service_manager.py
minder/examples/__init__.py
minder/examples/api_usage.py
minder/examples/basic_usage.py
minder/examples/launcher_usage.py
minder/examples/quick_upload_test.py
minder/examples/test_upload_apis.py
minder/examples/upload_package_example.py
minder/web/__init__.py
minder/web/gradio_app.py
mcp_minder-0.1.3.dist-info/METADATA
mcp_minder-0.1.3.dist-info/WHEEL
mcp_minder-0.1.3.dist-info/entry_points.txt
mcp_minder-0.1.3.dist-info/licenses/LICENSE
mcp_minder-0.1.3.dist-info/RECORD
