Metadata-Version: 2.4
Name: mcp_minder
Version: 0.1.3
Summary: MCP服务器管理框架 - 用于管理和监控MCP (Model Context Protocol) 服务器
Author-email: MCP Minder Team <contact@mcpminder.dev>
License: MIT
License-File: LICENSE
Keywords: framework,management,mcp,model-context-protocol,server
Classifier: Development Status :: 4 - Beta
Classifier: Intended Audience :: Developers
Classifier: License :: OSI Approved :: MIT License
Classifier: Operating System :: OS Independent
Classifier: Programming Language :: Python :: 3
Classifier: Programming Language :: Python :: 3.12
Classifier: Topic :: Software Development :: Libraries :: Python Modules
Classifier: Topic :: System :: Systems Administration
Requires-Python: >=3.12
Requires-Dist: asyncio-mqtt>=0.16.0
Requires-Dist: build>=1.0.0
Requires-Dist: fastapi>=0.104.0
Requires-Dist: fastmcp>=2.12.3
Requires-Dist: gradio>=4.0.0
Requires-Dist: httpx>=0.24.0
Requires-Dist: mcp>=1.13.1
Requires-Dist: psutil>=5.9.0
Requires-Dist: pydantic>=2.0.0
Requires-Dist: python-multipart>=0.0.6
Requires-Dist: pyyaml>=6.0
Requires-Dist: setuptools>=65.0.0
Requires-Dist: starlette>=0.27.0
Requires-Dist: twine>=4.0.0
Requires-Dist: uvicorn>=0.24.0
Provides-Extra: dev
Requires-Dist: black>=23.0.0; extra == 'dev'
Requires-Dist: build>=1.0.0; extra == 'dev'
Requires-Dist: flake8>=6.0.0; extra == 'dev'
Requires-Dist: httpx>=0.24.0; extra == 'dev'
Requires-Dist: isort>=5.12.0; extra == 'dev'
Requires-Dist: mypy>=1.0.0; extra == 'dev'
Requires-Dist: pre-commit>=3.0.0; extra == 'dev'
Requires-Dist: pytest-asyncio>=0.21.0; extra == 'dev'
Requires-Dist: pytest-cov>=4.0.0; extra == 'dev'
Requires-Dist: pytest>=7.0.0; extra == 'dev'
Requires-Dist: twine>=4.0.0; extra == 'dev'
